{
  "config": {
    "env_id": "HalfCheetah-v5",
    "output_dir": "results/ood/cheetah_pipeline",
    "wandb_project": "DT2-cheetah",
    "total_steps": 1000000,
    "ppo_fractions": [
      0.2,
      0.4,
      0.6,
      0.8,
      1.0
    ],
    "n_envs": 8,
    "n_steps": 2048,
    "batch_size": 1024,
    "learning_rate": 0.0003,
    "gamma": 0.97,
    "gae_lambda": 0.95,
    "clip_range": 0.2,
    "ent_coef": 0.01,
    "vf_coef": 0.5,
    "seed": 0,
    "rollout_steps": 10000,
    "q_epochs": 1000,
    "q_batch": 1024,
    "q_lr": 0.0003,
    "q_samples": 32,
    "dyn_epochs": 2000,
    "dyn_batch": 1024,
    "dyn_lr": 0.0003,
    "dyn_hidden_dim": 64,
    "dyn_val_fraction": 0.1,
    "dyn_early_stop_patience": 20,
    "dyn_min_epochs": 50,
    "dynamics_loss": "nll",
    "dynamics_models": [
      "supervised",
      "kendall"
    ],
    "lambda_td": 0.1,
    "lambda_rank": 0.1,
    "record_lambda_val": false,
    "rank_temperature": 1.0,
    "rank_rollout_horizon": 10,
    "rank_rollout_episodes": 128,
    "backbone": "resnet",
    "dyn_seq_len": 1,
    "dyn_seq_overlap": 0,
    "value_aware_only": false,
    "morel_ensemble_size": 4,
    "morel_hidden_dim": 200,
    "morel_epochs": 2000,
    "morel_batch_size": 1024,
    "morel_lr": 0.0003,
    "morel_threshold": null,
    "morel_threshold_mode": "mean_std",
    "morel_threshold_beta": 5.0,
    "morel_threshold_frac_max": 1.0,
    "morel_reward_offset": -1.0,
    "morel_halt_reward": null,
    "morel_no_bootstrap": false,
    "mopo_ensemble_size": 7,
    "mopo_elite_size": 5,
    "mopo_hidden_dim": 200,
    "mopo_hidden_layers": 4,
    "mopo_epochs": 2000,
    "mopo_batch_size": 1024,
    "mopo_lr": 0.0003,
    "mopo_holdout_size": 1000,
    "mopo_penalty_coef": 1.0,
    "mopo_no_bootstrap": false,
    "mopo_deterministic_dynamics_eval": false,
    "romi_ensemble_size": 4,
    "romi_hidden_dim": 200,
    "romi_hidden_layers": 4,
    "romi_weight_hidden_dim": 200,
    "romi_weight_hidden_layers": 4,
    "romi_epochs": 300,
    "romi_pretrain_epochs": 50,
    "romi_batch_size": 256,
    "romi_dynamics_lr": 0.0003,
    "romi_weight_lr": 0.0001,
    "romi_actor_lr": 0.0001,
    "romi_critic_lr": 0.0003,
    "romi_real_data_ratio": 0.5,
    "romi_rollout_horizon": 5,
    "romi_rollouts_per_epoch": 512,
    "romi_policy_updates_per_epoch": 200,
    "romi_dynamics_updates_per_epoch": 1,
    "romi_weight_updates_per_epoch": 1,
    "romi_uncertainty_scale": 0.1,
    "romi_uncertainty_samples": 10,
    "romi_weight_min": 0.5,
    "romi_weight_max": 2.0,
    "romi_model_buffer_capacity": 200000,
    "romi_bilevel_inner_lr": 0.0003,
    "romi_no_bootstrap": false,
    "romi_policy_pretrain_steps": 0,
    "romi_step_per_epoch": 0,
    "romi_rollout_freq": 0,
    "romi_rollout_batch_size": 0,
    "romi_dynamics_update_freq": 0,
    "romi_adv_train_steps": 1000,
    "romi_model_retain_epochs": 5,
    "romi_weight_input_mode": "sa_snext",
    "romi_deterministic_dynamics_eval": false,
    "eval_episodes": 20,
    "eval_rollouts": 20,
    "eval_horizon": 500,
    "eval_ood_policies": true,
    "ood_policy_types": [
      "random",
      "const_zero",
      "const_min",
      "const_max",
      "const_mid"
    ],
    "ood_eval_rollouts": 50,
    "ood_seed_offset": 10000,
    "device": "auto",
    "force_policy_training": false,
    "force_dataset_collection": false,
    "force_q_training": false,
    "force_dynamics_training": true,
    "results_only": false,
    "wandb_entity": null,
    "wandb_run_name": null,
    "wandb_mode": "online",
    "env_kwargs": {}
  },
  "num_transitions": 60000,
  "q_model_paths": {
    "ppo_frac_0": "results/test/cheetah_pipeline/q_models/ppo_frac_0.pt",
    "ppo_frac_200000": "results/test/cheetah_pipeline/q_models/ppo_frac_200000.pt",
    "ppo_frac_400000": "results/test/cheetah_pipeline/q_models/ppo_frac_400000.pt",
    "ppo_frac_600000": "results/test/cheetah_pipeline/q_models/ppo_frac_600000.pt",
    "ppo_frac_800000": "results/test/cheetah_pipeline/q_models/ppo_frac_800000.pt",
    "ppo_frac_1000000": "results/test/cheetah_pipeline/q_models/ppo_frac_1000000.pt"
  },
  "dynamics_paths": {
    "supervised": "results/ood/cheetah_pipeline/resnet/dynamics/dynamics_supervised.pt",
    "ranking": "results/ood/cheetah_pipeline/resnet/dynamics/dynamics_ranking.pt",
    "q_aware": {},
    "ranking_new": {
      "kendall": "results/ood/cheetah_pipeline/resnet/dynamics/dynamics_ranking_new_kendall.pt"
    },
    "value_aware": null,
    "morel": null,
    "morel_info": null,
    "mopo": null,
    "mopo_info": null,
    "romi": null,
    "romi_info": null
  },
  "morel_info": null,
  "mopo_info": null,
  "romi_info": null,
  "results": [
    {
      "name": "ppo_frac_0",
      "checkpoint": "results/test/cheetah_pipeline/policies/ppo_frac_0",
      "timesteps": 0,
      "q_estimate": -7.034521102905273,
      "dynamics": {
        "supervised": 5.883992671966553,
        "supervised_mse": 0.5408187508583069,
        "supervised_train_mse": 0.8091714382171631,
        "ranking_new": {
          "kendall": -20.464384078979492
        },
        "ranking_new_mse": {
          "kendall": 0.6729331016540527
        },
        "ranking_new_train_mse": {
          "kendall": 0.8896738886833191
        },
        "value_aware": null,
        "value_aware_mse": null,
        "value_aware_train_mse": null,
        "morel_pessimistic": null,
        "morel_pessimistic_stderr": null,
        "morel_unknown_rate": null,
        "morel_halted_fraction": null,
        "mopo_penalized": null,
        "mopo_penalized_stderr": null,
        "mopo_uncertainty_mean": null,
        "mopo_penalty_mean": null,
        "mopo_reward_mean": null,
        "romi_model_return": null,
        "romi_model_stderr": null,
        "romi_uncertainty_mean": null
      },
      "env_mc": -0.008654148602453454
    },
    {
      "name": "ppo_frac_200000",
      "checkpoint": "results/test/cheetah_pipeline/policies/ppo_frac_200000",
      "timesteps": 200000,
      "q_estimate": -5.476125717163086,
      "dynamics": {
        "supervised": -0.5671538710594177,
        "supervised_mse": 0.5237860083580017,
        "supervised_train_mse": 0.8447544574737549,
        "ranking_new": {
          "kendall": -18.446273803710938
        },
        "ranking_new_mse": {
          "kendall": 0.676135778427124
        },
        "ranking_new_train_mse": {
          "kendall": 0.9010637402534485
        },
        "value_aware": null,
        "value_aware_mse": null,
        "value_aware_train_mse": null,
        "morel_pessimistic": null,
        "morel_pessimistic_stderr": null,
        "morel_unknown_rate": null,
        "morel_halted_fraction": null,
        "mopo_penalized": null,
        "mopo_penalized_stderr": null,
        "mopo_uncertainty_mean": null,
        "mopo_penalty_mean": null,
        "mopo_reward_mean": null,
        "romi_model_return": null,
        "romi_model_stderr": null,
        "romi_uncertainty_mean": null
      },
      "env_mc": 7.275813433213843
    },
    {
      "name": "ppo_frac_400000",
      "checkpoint": "results/test/cheetah_pipeline/policies/ppo_frac_400000",
      "timesteps": 400000,
      "q_estimate": -3.1984384059906006,
      "dynamics": {
        "supervised": 6.325536727905273,
        "supervised_mse": 0.5368434190750122,
        "supervised_train_mse": 0.8001670837402344,
        "ranking_new": {
          "kendall": -8.3518648147583
        },
        "ranking_new_mse": {
          "kendall": 0.6525142788887024
        },
        "ranking_new_train_mse": {
          "kendall": 0.8783945441246033
        },
        "value_aware": null,
        "value_aware_mse": null,
        "value_aware_train_mse": null,
        "morel_pessimistic": null,
        "morel_pessimistic_stderr": null,
        "morel_unknown_rate": null,
        "morel_halted_fraction": null,
        "mopo_penalized": null,
        "mopo_penalized_stderr": null,
        "mopo_uncertainty_mean": null,
        "mopo_penalty_mean": null,
        "mopo_reward_mean": null,
        "romi_model_return": null,
        "romi_model_stderr": null,
        "romi_uncertainty_mean": null
      },
      "env_mc": 6.369737130489641
    },
    {
      "name": "ppo_frac_600000",
      "checkpoint": "results/test/cheetah_pipeline/policies/ppo_frac_600000",
      "timesteps": 600000,
      "q_estimate": -1.6638097763061523,
      "dynamics": {
        "supervised": 11.251604080200195,
        "supervised_mse": 0.5306870937347412,
        "supervised_train_mse": 0.8028060793876648,
        "ranking_new": {
          "kendall": 0.5736545324325562
        },
        "ranking_new_mse": {
          "kendall": 0.6639660596847534
        },
        "ranking_new_train_mse": {
          "kendall": 0.8652774691581726
        },
        "value_aware": null,
        "value_aware_mse": null,
        "value_aware_train_mse": null,
        "morel_pessimistic": null,
        "morel_pessimistic_stderr": null,
        "morel_unknown_rate": null,
        "morel_halted_fraction": null,
        "mopo_penalized": null,
        "mopo_penalized_stderr": null,
        "mopo_uncertainty_mean": null,
        "mopo_penalty_mean": null,
        "mopo_reward_mean": null,
        "romi_model_return": null,
        "romi_model_stderr": null,
        "romi_uncertainty_mean": null
      },
      "env_mc": 9.401122460843334
    },
    {
      "name": "ppo_frac_800000",
      "checkpoint": "results/test/cheetah_pipeline/policies/ppo_frac_800000",
      "timesteps": 800000,
      "q_estimate": -0.7752274870872498,
      "dynamics": {
        "supervised": 10.880374908447266,
        "supervised_mse": 0.5354820489883423,
        "supervised_train_mse": 0.8251997232437134,
        "ranking_new": {
          "kendall": 3.9646294116973877
        },
        "ranking_new_mse": {
          "kendall": 0.6581943035125732
        },
        "ranking_new_train_mse": {
          "kendall": 0.9018765091896057
        },
        "value_aware": null,
        "value_aware_mse": null,
        "value_aware_train_mse": null,
        "morel_pessimistic": null,
        "morel_pessimistic_stderr": null,
        "morel_unknown_rate": null,
        "morel_halted_fraction": null,
        "mopo_penalized": null,
        "mopo_penalized_stderr": null,
        "mopo_uncertainty_mean": null,
        "mopo_penalty_mean": null,
        "mopo_reward_mean": null,
        "romi_model_return": null,
        "romi_model_stderr": null,
        "romi_uncertainty_mean": null
      },
      "env_mc": 11.891387758663578
    },
    {
      "name": "ppo_frac_1000000",
      "checkpoint": "results/test/cheetah_pipeline/policies/ppo_frac_1000000",
      "timesteps": 1000000,
      "q_estimate": -0.7691123485565186,
      "dynamics": {
        "supervised": 15.032709121704102,
        "supervised_mse": 0.5381467342376709,
        "supervised_train_mse": 0.8421573638916016,
        "ranking_new": {
          "kendall": 2.7646279335021973
        },
        "ranking_new_mse": {
          "kendall": 0.6926807761192322
        },
        "ranking_new_train_mse": {
          "kendall": 0.9141694903373718
        },
        "value_aware": null,
        "value_aware_mse": null,
        "value_aware_train_mse": null,
        "morel_pessimistic": null,
        "morel_pessimistic_stderr": null,
        "morel_unknown_rate": null,
        "morel_halted_fraction": null,
        "mopo_penalized": null,
        "mopo_penalized_stderr": null,
        "mopo_uncertainty_mean": null,
        "mopo_penalty_mean": null,
        "mopo_reward_mean": null,
        "romi_model_return": null,
        "romi_model_stderr": null,
        "romi_uncertainty_mean": null
      },
      "env_mc": 10.277146206008933
    }
  ],
  "ood_results": [
    {
      "name": "ood_random_uniform",
      "deterministic_policy": false,
      "env_mc": -10.056578740254558,
      "dynamics": {
        "supervised": -5.350132942199707,
        "ranking_new": {
          "kendall": -13.133787155151367
        },
        "value_aware": null
      }
    },
    {
      "name": "ood_const_zero",
      "deterministic_policy": true,
      "env_mc": -0.3320250363432586,
      "dynamics": {
        "supervised": 7.627823352813721,
        "ranking_new": {
          "kendall": -19.069747924804688
        },
        "value_aware": null
      }
    },
    {
      "name": "ood_const_min",
      "deterministic_policy": true,
      "env_mc": -22.486553490084006,
      "dynamics": {
        "supervised": 23.02627944946289,
        "ranking_new": {
          "kendall": -13.57442569732666
        },
        "value_aware": null
      }
    },
    {
      "name": "ood_const_max",
      "deterministic_policy": true,
      "env_mc": -15.96909213595776,
      "dynamics": {
        "supervised": -29.611751556396484,
        "ranking_new": {
          "kendall": -8.024415969848633
        },
        "value_aware": null
      }
    },
    {
      "name": "ood_const_mid",
      "deterministic_policy": true,
      "env_mc": -0.3802690723356747,
      "dynamics": {
        "supervised": 6.511486053466797,
        "ranking_new": {
          "kendall": -20.05333137512207
        },
        "value_aware": null
      }
    }
  ],
  "ood_ranking_metrics": {
    "supervised": {
      "n_policies": 5.0,
      "spearman": 0.0,
      "kendall": 0.2,
      "top1_match": 0.0
    },
    "ranking_new_kendall": {
      "n_policies": 5.0,
      "spearman": -0.6,
      "kendall": -0.4,
      "top1_match": 0.0
    }
  }
}